marcsync/__init__.py
marcsync/collection.py
marcsync/entry.py
marcsync-0.1.0.dist-info/LICENSE
marcsync-0.1.0.dist-info/METADATA
marcsync-0.1.0.dist-info/WHEEL
marcsync-0.1.0.dist-info/top_level.txt
marcsync-0.1.0.dist-info/RECORD
