Metadata-Version: 2.1
Name: marcsync
Version: 0.1.0
Summary: A simple client for interacting with the MarcSync API
Author-email: MarcTheDev <marcthedev@marcsync.dev>
Project-URL: Homepage, https://marcsync.dev
Project-URL: Issues, https://github.com/marcsync/marcsync-python-client/issues
Classifier: Development Status :: 3 - Alpha
Classifier: Intended Audience :: Developers
Classifier: License :: OSI Approved :: MIT License
Classifier: Programming Language :: Python :: 3
Classifier: Programming Language :: Python :: 3.6
Classifier: Programming Language :: Python :: 3.7
Classifier: Programming Language :: Python :: 3.8
Classifier: Programming Language :: Python :: 3.9
Classifier: Programming Language :: Python :: 3.10
Classifier: Programming Language :: Python :: 3 :: Only
Classifier: Topic :: Software Development :: Libraries
Classifier: Topic :: Software Development :: Libraries :: Python Modules
Classifier: Typing :: Typed
Classifier: Operating System :: OS Independent
Requires-Python: >=3.6
License-File: LICENSE
